[{"id":"02000000","text":"经济学","pinyin":"jjx"},
{"id":"02010200","text":"国际经济与贸易","pinyin":"gjjjymy"},
{"id":"02010900","text":"金融工程","pinyin":"jrgc"},
{"id":"03000000","text":"法学","pinyin":"fx"},
{"id":"03030200","text":"社会工作","pinyin":"shgz"},
{"id":"05010100","text":"汉语言文学","pinyin":"hyywx"},
{"id":"05010300","text":"对外汉语","pinyin":"dwhy"},
{"id":"05020100","text":"英语","pinyin":"yy"},
{"id":"05020200","text":"俄语","pinyin":"ey"},
{"id":"05020700","text":"日语","pinyin":"ry"},
{"id":"05020900","text":"朝鲜语","pinyin":"cxy"},
{"id":"05030300","text":"广告学","pinyin":"ggx"},
{"id":"05040800","text":"艺术设计","pinyin":"yssj"},
{"id":"07010200","text":"信息与计算科学","pinyin":"xxyjskx"},
{"id":"07020200","text":"应用物理学","pinyin":"yywlx"},
{"id":"07030200","text":"应用化学","pinyin":"yyhx"},
{"id":"07040200","text":"生物技术","pinyin":"swjs"},
{"id":"07120100","text":"电子信息科学与技术","pinyin":"dzxxkxyjs"},
{"id":"07120200","text":"微电子学","pinyin":"wdzx"},
{"id":"07120300","text":"光信息科学与技术","pinyin":"gxxkxyjs"},
{"id":"07120700","text":"光电子技术科学","pinyin":"gdzjskx"},
{"id":"07130200","text":"材料化学","pinyin":"clhx"},
{"id":"07140100","text":"环境科学","pinyin":"hjgc"},
{"id":"08020300","text":"无机非金属材料工程","pinyin":"wjfjsclgc"},
{"id":"08021701","text":"新能源材料与器件","pinyin":"xnyclyqj"},
{"id":"08030100","text":"机械设计制造及其自动化","pinyin":"jxsjzzykzgc"},
{"id":"08030300","text":"工业设计","pinyin":"gysj"},
{"id":"08030400","text":"过程装备与控制工程","pinyin":"gczbykzgc"},
{"id":"08030700","text":"机械电子工程","pinyin":"jxdzgc"},
{"id":"08040100","text":"测控技术与仪器","pinyin":"ctjsyyq"},
{"id":"08060100","text":"电气工程及其自动化","pinyin":"dqgcjqzdh"},
{"id":"08060200","text":"自动化","pinyin":"zdh"},
{"id":"08060300","text":"电子信息工程","pinyin":"dzxxgc"},
{"id":"08060400","text":"通信工程","pinyin":"txgc"},
{"id":"08060500","text":"计算机科学与技术","pinyin":"jsjkxyjs"},
{"id":"08060600","text":"电子科学与技术","pinyin":"dzkxjs"},
{"id":"08060700","text":"生物医学工程","pinyin":"swyxgc"},
{"id":"08061100","text":"软件工程","pinyin":"rjgc"},
{"id":"08061300","text":"网络工程","pinyin":"wlgc"},
{"id":"08061600","text":"光电信息工程","pinyin":"gdxxgc"},
{"id":"08100100","text":"环境工程","pinyin":"hjgc"},
{"id":"08110100","text":"化学工程与工艺","pinyin":"hxgcygy"},
{"id":"08160200","text":"探测制导与控制技术","pinyin":"tczdykzjs"},
{"id":"08160600","text":"信息对抗技术","pinyin":"xxdkjs"},
{"id":"08180100","text":"生物工程","pinyin":"swgc"},
{"id":"11010200","text":"信息管理与信息系统","pinyin":"xxglyxxxt"},
{"id":"11020100","text":"工商管理","pinyin":"gsgl"},
{"id":"11020200","text":"市场营销","pinyin":"scyx"},
{"id":"11020300","text":"会计学","pinyin":"shx"},
{"id":"11030300","text":"劳动与社会保障","pinyin":"ldyshbz"}]